django_billdesk/__init__.py
django_billdesk/checksum.py
django_billdesk/gen_message.py
django_billdesk/responseMsg.py
django_billdesk-0.0.2.dist-info/LICENSE
django_billdesk-0.0.2.dist-info/METADATA
django_billdesk-0.0.2.dist-info/WHEEL
django_billdesk-0.0.2.dist-info/top_level.txt
django_billdesk-0.0.2.dist-info/RECORD
