Metadata-Version: 2.1
Name: django-billdesk
Version: 0.0.2
Summary: A tool to integrate BillDesk in Django Site
Home-page: https://github.com/FerociousCentaur/py-billdesk
Author: Vivek Anand
Author-email: vivek17212797@gmail.com
License: MIT
Keywords: billdesk python-billdesk py-billdesk django-billdesk
Platform: UNKNOWN
Classifier: Development Status :: 4 - Beta
Classifier: License :: OSI Approved :: MIT License
Classifier: Programming Language :: Python
Classifier: Programming Language :: Python :: 3.5
Classifier: Programming Language :: Python :: 3.6
Classifier: Topic :: Software Development :: Libraries
Classifier: Topic :: Software Development :: Libraries :: Python Modules
Classifier: Intended Audience :: Developers
Requires-Python: >=3.5
